Workbook

Sheet Cover
B3: RevSpring, Inc.
B4: LBO / Financial Model | Healthcare PE Workshop
B6: Prepared by Morsebridge Healthcare | June 2024 | CONFIDENTIAL
B9: DEAL SUMMARY
B10: Target Company | C10: RevSpring, Inc.
B11: Headquarters | C11: Nashville, Tennessee
B12: Sub-Sector | C12: Patient Engagement / Revenue Cycle Management
B13: Deal Type | C13: Secondary Buyout (GTCR → Frazier Healthcare Partners)
B14: Transaction Date | C14: March 12, 2024
B15: Enterprise Value | C15: ~$1,300M
B16: Equity Value (implied) | C16: ~$990M
B17: Net Debt at Close | C17: ~$310M
B18: EV / Revenue (FY2023) | C18: ~5.2x
B19: EV / EBITDA (FY2023) | C19: ~19.4x
B20: Entry Leverage | C20: ~4.3x Net Debt / EBITDA
B21: Sell-Side Advisors | C21: Morgan Stanley; Triple Tree
B22: Target Return | C22: 3.0x+ MOIC | 25%+ IRR
B24: MODEL STRUCTURE
B25: Cover | C25: Deal summary and model navigation
B26: Assumptions | C26: All hardcoded inputs and scenario toggles
B27: Income Statement | C27: Revenue build, EBITDA, and net income (FY2020-FY2026E)
B28: Balance Sheet | C28: Assets, liabilities, and equity (FY2020-FY2026E)
B29: Cash Flow Statement | C29: Operating, investing, financing cash flows
B30: Debt Schedule | C30: Debt tranches, amortisation, PIK, and covenant tracking
B31: LBO Returns | C31: Entry/exit assumptions, MOIC, IRR, and sensitivity tables
B33: COLOR KEY
B34: Blue text | C34: Hardcoded input / assumption
B35: Black text | C35: Formula / calculated output
B36: Green text | C36: Cross-sheet link
B37: Blue background | C37: Subtotal or key output row
B38: Yellow background | C38: Cell requiring attention / update

Sheet Assumptions
B1: ASSUMPTIONS & SCENARIO INPUTS
B3: ACTIVE SCENARIO | D3: Bear | E3: Base | F3: Bull
B4: Select Scenario (Bear / Base / Bull): | C4: Base | D4: Bear | E4: Base | F4: Bull
B6: REVENUE ASSUMPTIONS
B7: Metric | C7: FY2020A | D7: FY2021A | E7: FY2022A | F7: FY2023A | G7: FY2024E
B8: Revenue ($M) | C8: 162.4 | D8: 188.7 | E8: 220.3 | F8: 248.1 | G8: 300
B9: YoY Revenue Growth | C9: ="-" -> - | D9: =(Assumptions!D8-Assumptions!C8)/Assumptions!C8 -> 0.16194581 | E9: =(Assumptions!E8-Assumptions!D8)/Assumptions!D8 -> 0.16746158 | F9: =(Assumptions!F8-Assumptions!E8)/Assumptions!E8 -> 0.12619156 | G9: =(Assumptions!G8-Assumptions!F8)/Assumptions!F8 -> 0.20918984
B10: Recurring Revenue % | C10: 0.78 | D10: 0.79 | E10: 0.8 | F10: 0.81 | G10: 0.82
B11: NRR (Net Revenue Retention) | C11: 1.05 | D11: 1.06 | E11: 1.07 | F11: 1.08 | G11: 1.08
B13: PROJECTION ASSUMPTIONS (FY2025E - FY2026E)
B14: Metric | C14: Bear | D14: Base | E14: Bull | F14: FY2025E (active) | G14: FY2026E (active)
B15: Revenue Growth FY2025E | C15: 0.08 | D15: 0.12 | E15: 0.16 | F15: =IF($C$4="Bear",C15,IF($C$4="Bull",E15,D15)) -> 0.12 | G15: =IF($C$4="Bear",C15,IF($C$4="Bull",E15,D15)) -> 0.12
B16: Revenue Growth FY2026E | C16: 0.08 | D16: 0.13 | E16: 0.16 | F16: =IF($C$4="Bear",C16,IF($C$4="Bull",E16,D16)) -> 0.13 | G16: =IF($C$4="Bear",C16,IF($C$4="Bull",E16,D16)) -> 0.13
B17: Gross Margin FY2025E | C17: 0.525 | D17: 0.535 | E17: 0.545 | F17: =IF($C$4="Bear",C17,IF($C$4="Bull",E17,D17)) -> 0.535 | G17: =IF($C$4="Bear",C17,IF($C$4="Bull",E17,D17)) -> 0.535
B18: Gross Margin FY2026E | C18: 0.53 | D18: 0.54 | E18: 0.55 | F18: =IF($C$4="Bear",C18,IF($C$4="Bull",E18,D18)) -> 0.54 | G18: =IF($C$4="Bear",C18,IF($C$4="Bull",E18,D18)) -> 0.54
B19: EBITDA Margin FY2025E | C19: 0.26 | D19: 0.272 | E19: 0.28 | F19: =IF($C$4="Bear",C19,IF($C$4="Bull",E19,D19)) -> 0.272 | G19: =IF($C$4="Bear",C19,IF($C$4="Bull",E19,D19)) -> 0.272
B20: EBITDA Margin FY2026E | C20: 0.262 | D20: 0.275 | E20: 0.285 | F20: =IF($C$4="Bear",C20,IF($C$4="Bull",E20,D20)) -> 0.275 | G20: =IF($C$4="Bear",C20,IF($C$4="Bull",E20,D20)) -> 0.275
B21: D&A % Revenue | C21: 0.082 | D21: 0.082 | E21: 0.082 | F21: =IF($C$4="Bear",C21,IF($C$4="Bull",E21,D21)) -> 0.082 | G21: =IF($C$4="Bear",C21,IF($C$4="Bull",E21,D21)) -> 0.082
B22: Interest Rate (avg) | C22: 0.085 | D22: 0.085 | E22: 0.085 | F22: =IF($C$4="Bear",C22,IF($C$4="Bull",E22,D22)) -> 0.085 | G22: =IF($C$4="Bear",C22,IF($C$4="Bull",E22,D22)) -> 0.085
B23: Tax Rate | C23: 0.25 | D23: 0.25 | E23: 0.25 | F23: =IF($C$4="Bear",C23,IF($C$4="Bull",E23,D23)) -> 0.25 | G23: =IF($C$4="Bear",C23,IF($C$4="Bull",E23,D23)) -> 0.25
B25: MARGIN ASSUMPTIONS (HISTORICAL)
B26: Metric | C26: FY2020A | D26: FY2021A | E26: FY2022A | F26: FY2023A | G26: FY2024E
B27: Gross Margin | C27: 0.5 | D27: 0.51 | E27: 0.52 | F27: 0.525 | G27: 0.53
B28: EBITDA Margin | C28: 0.235 | D28: 0.25 | E28: 0.26 | F28: 0.27 | G28: 0.275
B29: D&A % Revenue | C29: 0.087 | D29: 0.084 | E29: 0.083 | F29: 0.083 | G29: 0.08
B30: Capex % Revenue | C30: 0.04 | D30: 0.04 | E30: 0.038 | F30: 0.038 | G30: 0.036
B31: NWC % Revenue | C31: 0.06 | D31: 0.058 | E31: 0.056 | F31: 0.054 | G31: 0.052

Sheet Income Statement
B1: INCOME STATEMENT | RevSpring, Inc. ($M)
B3: Line Item | C3: FY2020A | D3: FY2021A | E3: FY2022A | F3: FY2023A | G3: FY2024E | H3: FY2025E | I3: FY2026E
B4: REVENUE
B5: SaaS / Subscription Revenue | C5: 78 | D5: 94.3 | E5: 114.6 | F5: 131.5 | G5: 165 | H5: =ROUND(H9*Assumptions!C27,1) -> 169.5 | I5: =ROUND(I9*Assumptions!C27,1) -> 260.2
B6: Transaction / Payment Revenue | C6: 45.5 | D6: 50.9 | E6: 57.3 | F6: 64.5 | G6: 75 | H6: =ROUND(H9*Assumptions!C28,1) -> 79.7 | I6: =ROUND(I9*Assumptions!C28,1) -> 122.3
B7: Print & Mail Revenue | C7: 27.6 | D7: 30.2 | E7: 33 | F7: 34.7 | G7: 39 | H7: =ROUND(H9*Assumptions!C29,1) -> 29.5 | I7: =ROUND(I9*Assumptions!C29,1) -> 45.3
B8: Professional Services | C8: =C9-C5-C6-C7 -> 11.3 | D8: =D9-D5-D6-D7 -> 13.3 | E8: =E9-E5-E6-E7 -> 15.4 | F8: =F9-F5-F6-F7 -> 17.4 | G8: =G9-G5-G6-G7 -> 21 | H8: =H9-H5-H6-H7 -> 60.3 | I8: =I9-I5-I6-I7 -> 92.6
B9: Total Revenue | C9: 162.4 | D9: 188.7 | E9: 220.3 | F9: 248.1 | G9: 300 | H9: =ROUND(G9*(1+Assumptions!F16),1) -> 339 | I9: =ROUND(H9*(1+Assumptions!F17),1) -> 520.4
B10: YoY Revenue Growth | C10: ="-" -> - | D10: =(D9-C9)/C9 -> 0.16194581 | E10: =(E9-D9)/D9 -> 0.16746158 | F10: =(F9-E9)/E9 -> 0.12619156 | G10: =(G9-F9)/F9 -> 0.20918984 | H10: =(H9-G9)/G9 -> 0.13 | I10: =(I9-H9)/H9 -> 0.53510324
B11: COST STRUCTURE
B12: Cost of Revenue | C12: =C9-C13 -> 81.2 | D12: =D9-D13 -> 92.5 | E12: =E9-E13 -> 105.7 | F12: =F9-F13 -> 117.8 | G12: =G9-G13 -> 141 | H12: =H9-H13 -> 310.9 | I12: =I9-I13 -> 477.2
B13: Gross Profit | C13: 81.2 | D13: 96.2 | E13: 114.6 | F13: 130.3 | G13: 159 | H13: =ROUND(H9*Assumptions!F29,1) -> 28.1 | I13: =ROUND(I9*Assumptions!F29,1) -> 43.2
B14: Gross Margin % | C14: =C13/C9 -> 0.5 | D14: =D13/D9 -> 0.50980392 | E14: =E13/E9 -> 0.52019973 | F14: =F13/F9 -> 0.52519146 | G14: =G13/G9 -> 0.53 | H14: =H13/H9 -> 0.082890855 | I14: =I13/I9 -> 0.083013067
B15: EBITDA BRIDGE
B16: Sales & Marketing | C16: 13 | D16: 15.1 | E16: 17.6 | F16: 19.8 | G16: 24 | H16: =ROUND(H9*0.08,1) -> 27.1 | I16: =ROUND(I9*0.08,1) -> 41.6
B17: Research & Development | C17: 8.1 | D17: 9.4 | E17: 11 | F17: 12.4 | G17: 15 | H17: =ROUND(H9*0.05,1) -> 17 | I17: =ROUND(I9*0.05,1) -> 26
B18: General & Administrative | C18: =C19-C16-C17 -> 21.9 | D18: =D19-D16-D17 -> 24.5 | E18: =E19-E16-E17 -> 28.7 | F18: =F19-F16-F17 -> 31.1 | G18: =G19-G16-G17 -> 37.5 | H18: =H19-H16-H17 -> -44.1 | I18: =I19-I16-I17 -> -67.6
B19: Total OpEx (excl. D&A) | C19: =C13-C20 -> 43 | D19: =D13-D20 -> 49 | E19: =E13-E20 -> 57.3 | F19: =F13-F20 -> 63.3 | G19: =G13-G20 -> 76.5 | H19: =H13-H20 -> 0 | I19: =I13-I20 -> 0
B20: EBITDA | C20: 38.2 | D20: 47.2 | E20: 57.3 | F20: 67 | G20: 82.5 | H20: =ROUND(H9*Assumptions!F29,1) -> 28.1 | I20: =ROUND(I9*Assumptions!F29,1) -> 43.2
B21: EBITDA Margin % | C21: =C20/C9 -> 0.23522167 | D21: =D20/D9 -> 0.25013249 | E21: =E20/E9 -> 0.26009986 | F21: =F20/F9 -> 0.2700524 | G21: =G20/G9 -> 0.275 | H21: =H20/H9 -> 0.082890855 | I21: =I20/I9 -> 0.083013067
B22: BELOW EBITDA
B23: Depreciation & Amortisation | C23: 14.1 | D23: 15.9 | E23: 18.2 | F23: 20.6 | G23: 24 | H23: =ROUND(H9*Assumptions!C30,1) -> 13.6 | I23: =ROUND(I9*Assumptions!C30,1) -> 20.8
B24: EBIT | C24: =C20-C23 -> 24.1 | D24: =D20-D23 -> 31.3 | E24: =E20-E23 -> 39.1 | F24: =F20-F23 -> 46.4 | G24: =G20-G23 -> 58.5 | H24: =H20-H23 -> 14.5 | I24: =I20-I23 -> 22.4
B25: Interest Expense | C25: 18.2 | D25: 18.6 | E25: 20.1 | F25: 22.4 | G25: 24.1 | H25: =ROUND('Debt Schedule'!H15*Assumptions!C31,1) -> 0 | I25: =ROUND('Debt Schedule'!I15*Assumptions!C31,1) -> 0
B26: EBT (Earnings Before Tax) | C26: =C24-C25 -> 5.9 | D26: =D24-D25 -> 12.7 | E26: =E24-E25 -> 19 | F26: =F24-F25 -> 24 | G26: =G24-G25 -> 34.4 | H26: =H24-H25 -> 14.5 | I26: =I24-I25 -> 22.4
B27: Income Tax Expense | C27: =IF(C26>0,C26*Assumptions!C31,0) -> 0.354 | D27: =IF(D26>0,D26*Assumptions!C31,0) -> 0.762 | E27: =IF(E26>0,E26*Assumptions!C31,0) -> 1.14 | F27: =IF(F26>0,F26*Assumptions!C31,0) -> 1.44 | G27: =IF(G26>0,G26*Assumptions!C31,0) -> 2.064 | H27: =IF(H26>0,H26*Assumptions!C31,0) -> 0.87 | I27: =IF(I26>0,I26*Assumptions!C31,0) -> 1.344
B28: Net Income (Adjusted) | C28: =C26-C27 -> 5.546 | D28: =D26-D27 -> 11.938 | E28: =E26-E27 -> 17.86 | F28: =F26-F27 -> 22.56 | G28: =G26-G27 -> 32.336 | H28: =H26-H27 -> 13.63 | I28: =I26-I27 -> 21.056
B29: Net Margin % | C29: =IF(C9>0,C28/C9,0) -> 0.034150246 | D29: =IF(D9>0,D28/D9,0) -> 0.063264441 | E29: =IF(E9>0,E28/E9,0) -> 0.081071266 | F29: =IF(F9>0,F28/F9,0) -> 0.090931076 | G29: =IF(G9>0,G28/G9,0) -> 0.10778667 | H29: =IF(H9>0,H28/H9,0) -> 0.04020649 | I29: =IF(I9>0,I28/I9,0) -> 0.040461184

Sheet Balance Sheet
B1: BALANCE SHEET | RevSpring, Inc. ($M)
B3: Line Item | C3: FY2020A | D3: FY2021A | E3: FY2022A | F3: FY2023A | G3: FY2024E | H3: FY2025E | I3: FY2026E
B4: CURRENT ASSETS
B5: Cash & Equivalents | C5: 18.2 | D5: 22.1 | E5: 26.4 | F5: 18.7 | G5: 28.5 | H5: =ROUND(G5*1.05,1) -> 29.9 | I5: =ROUND(H5*1.05,1) -> 31.4
B6: Accounts Receivable | C6: 19.5 | D6: 22.6 | E6: 26.4 | F6: 29.8 | G6: 36 | H6: =ROUND(G6*1.05,1) -> 37.8 | I6: =ROUND(H6*1.05,1) -> 39.7
B7: Prepaid & Other Current | C7: 6.2 | D7: 7.1 | E7: 8.3 | F7: 9.4 | G7: 11.4 | H7: =ROUND(G7*1.05,1) -> 12 | I7: =ROUND(H7*1.05,1) -> 12.6
B8: Total Current Assets | C8: =SUM(C5:C7) -> 43.9 | D8: =SUM(D5:D7) -> 51.8 | E8: =SUM(E5:E7) -> 61.1 | F8: =SUM(F5:F7) -> 57.9 | G8: =SUM(G5:G7) -> 75.9 | H8: =SUM(H5:H7) -> 79.7 | I8: =SUM(I5:I7) -> 83.7
B9: NON-CURRENT ASSETS
B10: Net PP&E | C10: 22.4 | D10: 24.1 | E10: 26.8 | F10: 28.9 | G10: 33 | H10: =ROUND(G10*1.02,1) -> 33.7 | I10: =ROUND(H10*1.02,1) -> 34.4
B11: Goodwill & Intangibles | C11: 189.2 | D11: 190.8 | E11: 192.1 | F11: 189.4 | G11: 187 | H11: =ROUND(G11*1.02,1) -> 190.7 | I11: =ROUND(H11*1.02,1) -> 194.5
B12: Other Long-Term Assets | C12: 8.4 | D12: 9.1 | E12: 10.2 | F12: 11.3 | G12: 12.8 | H12: =ROUND(G12*1.02,1) -> 13.1 | I12: =ROUND(H12*1.02,1) -> 13.4
B13: Total Assets | C13: =C8+SUM(C10:C12) -> 263.9 | D13: =D8+SUM(D10:D12) -> 275.8 | E13: =E8+SUM(E10:E12) -> 290.2 | F13: =F8+SUM(F10:F12) -> 287.5 | G13: =G8+SUM(G10:G12) -> 308.7 | H13: =H8+SUM(H10:H12) -> 317.2 | I13: =I8+SUM(I10:I12) -> 326
B14: LIABILITIES
B15: Accounts Payable | C15: 8.1 | D15: 9.3 | E15: 10.8 | F15: 12.2 | G15: 14.7 | H15: =ROUND(G15*1.03,1) -> 15.1 | I15: =ROUND(H15*1.03,1) -> 15.6
B16: Deferred Revenue | C16: 14.2 | D16: 16.5 | E16: 19.3 | F16: 21.7 | G16: 26.2 | H16: =ROUND(G16*1.03,1) -> 27 | I16: =ROUND(H16*1.03,1) -> 27.8
B17: Accrued Liabilities | C17: 9.4 | D17: 10.9 | E17: 12.7 | F17: 14.3 | G17: 17.3 | H17: =ROUND(G17*1.03,1) -> 17.8 | I17: =ROUND(H17*1.03,1) -> 18.3
B18: Total Debt (net current) | C18: 310 | D18: 308.5 | E18: 307 | F18: 310 | G18: 306 | H18: =ROUND(G18*1.03,1) -> 315.2 | I18: =ROUND(H18*1.03,1) -> 324.7
B19: Total Liabilities | C19: =SUM(C15:C18) -> 341.7 | D19: =SUM(D15:D18) -> 345.2 | E19: =SUM(E15:E18) -> 349.8 | F19: =SUM(F15:F18) -> 358.2 | G19: =SUM(G15:G18) -> 364.2 | H19: =SUM(H15:H18) -> 375.1 | I19: =SUM(I15:I18) -> 386.4
B20: EQUITY
B21: Share Capital + APIC | C21: 680 | D21: 680 | E21: 680 | F21: 680 | G21: 680 | H21: =G21+'Income Statement'!G28 -> 712.336 | I21: =H21+'Income Statement'!H28 -> 725.966
B22: Retained Earnings (Deficit) | C22: -388.2 | D22: -371.8 | E22: -350.2 | F22: -322.6 | G22: -278.5 | H22: =G22+'Income Statement'!G28 -> -246.164 | I22: =H22+'Income Statement'!H28 -> -232.534
B23: Total Equity | C23: =C21+C22 -> 291.8 | D23: =D21+D22 -> 308.2 | E23: =E21+E22 -> 329.8 | F23: =F21+F22 -> 357.4 | G23: =G21+G22 -> 401.5 | H23: =H21+H22 -> 466.172 | I23: =I21+I22 -> 493.432
B24: Total Liabilities + Equity | C24: =C19+C23 -> 633.5 | D24: =D19+D23 -> 653.4 | E24: =E19+E23 -> 679.6 | F24: =F19+F23 -> 715.6 | G24: =G19+G23 -> 765.7 | H24: =H19+H23 -> 841.272 | I24: =I19+I23 -> 879.832
B25: Balance Check (Assets - L+E) | C25: =C13-C24 -> -369.6 | D25: =D13-D24 -> -377.6 | E25: =E13-E24 -> -389.4 | F25: =F13-F24 -> -428.1 | G25: =G13-G24 -> -457 | H25: =H13-H24 -> -524.072 | I25: =I13-I24 -> -553.832

Sheet Cash Flow Statement
B1: CASH FLOW STATEMENT | RevSpring, Inc. ($M)
B3: Line Item | C3: FY2020A | D3: FY2021A | E3: FY2022A | F3: FY2023A | G3: FY2024E | H3: FY2025E | I3: FY2026E
B4: OPERATING ACTIVITIES
B5: Net Income | C5: ='Income Statement'!C28 -> 5.546 | D5: ='Income Statement'!D28 -> 11.938 | E5: ='Income Statement'!E28 -> 17.86 | F5: ='Income Statement'!F28 -> 22.56 | G5: ='Income Statement'!G28 -> 32.336 | H5: ='Income Statement'!H28 -> 13.63 | I5: ='Income Statement'!I28 -> 21.056
B6: Add: D&A | C6: ='Income Statement'!C23 -> 14.1 | D6: ='Income Statement'!D23 -> 15.9 | E6: ='Income Statement'!E23 -> 18.2 | F6: ='Income Statement'!F23 -> 20.6 | G6: ='Income Statement'!G23 -> 24 | H6: ='Income Statement'!H23 -> 13.6 | I6: ='Income Statement'!I23 -> 20.8
B7: Changes in Working Capital | C7: -4.8 | D7: -5.2 | E7: -6.1 | F7: -6.4 | G7: -7.4 | H7: =ROUND(-'Income Statement'!H9*0.025,1) -> -8.5 | I7: =ROUND(-'Income Statement'!I9*0.025,1) -> -13
B8: Other Non-Cash Items | C8: 1.2 | D8: 1.4 | E8: 1.6 | F8: 1.8 | G8: 2.1 | H8: =ROUND('Income Statement'!H9*0.007,1) -> 2.4 | I8: =ROUND('Income Statement'!I9*0.007,1) -> 3.6
B9: Cash from Operations | C9: =SUM(C5:C8) -> 16.046 | D9: =SUM(D5:D8) -> 24.038 | E9: =SUM(E5:E8) -> 31.56 | F9: =SUM(F5:F8) -> 38.56 | G9: =SUM(G5:G8) -> 51.036 | H9: =SUM(H5:H8) -> 21.13 | I9: =SUM(I5:I8) -> 32.456
B10: INVESTING ACTIVITIES
B11: Capital Expenditures | C11: -6.5 | D11: -7.5 | E11: -8.4 | F11: -9.4 | G11: -10.8 | H11: =ROUND(-'Income Statement'!H9*Assumptions!C30,1) -> -13.6 | I11: =ROUND(-'Income Statement'!I9*Assumptions!C30,1) -> -20.8
B12: Acquisitions (net) | C12: 0 | D12: 0 | E12: 0 | F12: 0 | G12: 0 | H12: 0 | I12: 0
B13: Cash from Investing | C13: =C11+C12 -> -6.5 | D13: =D11+D12 -> -7.5 | E13: =E11+E12 -> -8.4 | F13: =F11+F12 -> -9.4 | G13: =G11+G12 -> -10.8 | H13: =H11+H12 -> -13.6 | I13: =I11+I12 -> -20.8
B14: FINANCING ACTIVITIES
B15: Debt Repayment | C15: -1.5 | D15: -1.5 | E15: -1.5 | F15: -1.5 | G15: -4 | H15: -4 | I15: -4
B16: Equity Issuance / (Buyback) | C16: 0 | D16: 0 | E16: 0 | F16: 0 | G16: 0 | H16: 0 | I16: 0
B17: Cash from Financing | C17: =C15+C16 -> -1.5 | D17: =D15+D16 -> -1.5 | E17: =E15+E16 -> -1.5 | F17: =F15+F16 -> -1.5 | G17: =G15+G16 -> -4 | H17: =H15+H16 -> -4 | I17: =I15+I16 -> -4
B19: Net Change in Cash | C19: =C9+C13+C17 -> 8.046 | D19: =D9+D13+D17 -> 15.038 | E19: =E9+E13+E17 -> 21.66 | F19: =F9+F13+F17 -> 27.66 | G19: =G9+G13+G17 -> 36.236 | H19: =H9+H13+H17 -> 3.53 | I19: =I9+I13+I17 -> 7.656
B20: Opening Cash | C20: 14.2 | D20: 18.2 | E20: 22.1 | F20: 26.4 | G20: 18.7 | H20: =G21 -> 54.936 | I20: =H21 -> 58.466
B21: Closing Cash | C21: =C20+C19 -> 22.246 | D21: =D20+D19 -> 33.238 | E21: =E20+E19 -> 43.76 | F21: =F20+F19 -> 54.06 | G21: =G20+G19 -> 54.936 | H21: =H20+H19 -> 58.466 | I21: =I20+I19 -> 66.122

Sheet Debt Schedule
B1: DEBT SCHEDULE | RevSpring, Inc. ($M)
B3: Line Item | C3: FY2020A | D3: FY2021A | E3: FY2022A | F3: FY2023A | G3: FY2024E | H3: FY2025E | I3: FY2026E
B4: TRANCHE DETAIL
B5: Senior Secured Term Loan B
B6: Opening Balance | C6: 240 | D6: 238.8 | E6: 237.5 | F6: 236.3 | G6: 235 | H6: 233.8 | I6: 232.5
B7: Interest Rate (SOFR+spread): 4.50% | C7: 0.045 | D7: 0.045 | E7: 0.045 | F7: 0.045 | G7: 0.045 | H7: 0.045 | I7: 0.045
B8: Closing Balance | C8: 237.6 | D8: 236.4 | E8: 235.1 | F8: 233.9 | G8: 232.7 | H8: 231.5 | I8: 232.5
B9: Revolving Credit Facility
B10: Opening Balance | C10: 0 | D10: 0 | E10: 0 | F10: 0 | G10: 0 | H10: 0 | I10: 0
B11: Interest Rate (SOFR+spread): 4.25% | C11: 0.0425 | D11: 0.0425 | E11: 0.0425 | F11: 0.0425 | G11: 0.0425 | H11: 0.0425 | I11: 0.0425
B12: Closing Balance | C12: 0 | D12: 0 | E12: 0 | F12: 0 | G12: 0 | H12: 0 | I12: 0
B13: Second Lien / Mezz
B14: Opening Balance | C14: 70 | D14: 69.7 | E14: 69.5 | F14: 73.7 | G14: 71 | H14: 69 | I14: 67
B15: Interest Rate (SOFR+spread): 8.25% | C15: 0.0825 | D15: 0.0825 | E15: 0.0825 | F15: 0.0825 | G15: 0.0825 | H15: 0.0825 | I15: 0.0825
B16: Closing Balance | C16: 69.3 | D16: 69 | E16: 68.8 | F16: 73 | G16: 70.3 | H16: 68.3 | I16: 67
B17: Total Debt (Closing) | C17: =C8+C12+C16 -> 306.9 | D17: =D8+D12+D16 -> 305.4 | E17: =E8+E12+E16 -> 303.9 | F17: =F8+F12+F16 -> 306.9 | G17: =G8+G12+G16 -> 303 | H17: =H8+H12+H16 -> 299.8 | I17: =I8+I12+I16 -> 299.5
B19: COVENANT TRACKING
B20: Covenant Metric | C20: FY2020A | D20: FY2021A | E20: FY2022A | F20: FY2023A | G20: FY2024E | H20: FY2025E | I20: FY2026E
B21: Net Debt | C21: =C17-'Balance Sheet'!C5 -> 288.7 | D21: =D17-'Balance Sheet'!D5 -> 283.3 | E21: =E17-'Balance Sheet'!E5 -> 277.5 | F21: =F17-'Balance Sheet'!F5 -> 288.2 | G21: =G17-'Balance Sheet'!G5 -> 274.5 | H21: =H17-'Balance Sheet'!H5 -> 269.9 | I21: =I17-'Balance Sheet'!I5 -> 268.1
B22: EBITDA (from IS) | C22: ='Income Statement'!C20 -> 38.2 | D22: ='Income Statement'!D20 -> 47.2 | E22: ='Income Statement'!E20 -> 57.3 | F22: ='Income Statement'!F20 -> 67 | G22: ='Income Statement'!G20 -> 82.5 | H22: ='Income Statement'!H20 -> 28.1 | I22: ='Income Statement'!I20 -> 43.2
B23: Net Debt / EBITDA | C23: =IF(C22>0,C21/C22,"-") -> 7.5575916 | D23: =IF(D22>0,D21/D22,"-") -> 6.0021186 | E23: =IF(E22>0,E21/E22,"-") -> 4.8429319 | F23: =IF(F22>0,F21/F22,"-") -> 4.3014925 | G23: =IF(G22>0,G21/G22,"-") -> 3.3272727 | H23: =IF(H22>0,H21/H22,"-") -> 9.6049822 | I23: =IF(I22>0,I21/I22,"-") -> 6.2060185
B24: Covenant Limit | C24: 6.5 | D24: 6.5 | E24: 6.5 | F24: 6.5 | G24: 6.5 | H24: 6.5 | I24: 6.5
B25: Headroom | C25: =IF(ISNUMBER(C23),C24-C23,"-") -> -1.0575916 | D25: =IF(ISNUMBER(D23),D24-D23,"-") -> 0.49788136 | E25: =IF(ISNUMBER(E23),E24-E23,"-") -> 1.6570681 | F25: =IF(ISNUMBER(F23),F24-F23,"-") -> 2.1985075 | G25: =IF(ISNUMBER(G23),G24-G23,"-") -> 3.1727273 | H25: =IF(ISNUMBER(H23),H24-H23,"-") -> -3.1049822 | I25: =IF(ISNUMBER(I23),I24-I23,"-") -> 0.29398148

Sheet LBO Returns
B1: LBO RETURNS ANALYSIS | RevSpring, Inc.
B3: ENTRY ASSUMPTIONS
B4: Entry Date | C4: March 2024
B5: Entry Enterprise Value ($M) | C5: $1,300.0
B6: Entry Net Debt ($M) | C6: $310.0
B7: Entry Equity Value ($M) | C7: $990.0
B8: Entry EBITDA ($M, FY2023A) | C8: $67.0
B9: Entry EV / EBITDA | C9: 19.4x
B10: Entry EV / Revenue | C10: 5.2x
B11: Management Rollover ($M) | C11: $45.0
B12: Frazier Equity Contribution ($M) | C12: $550.0
B13: Co-Invest (NEA + 22C) ($M) | C13: $180.0
B15: EXIT ASSUMPTIONS (SCENARIOS)
B16: Metric | C16: Bear (5yr) | D16: Base (5yr) | E16: Bull (5yr) | F16: Base (4yr) | G16: Base (7yr)
B17: Hold Period (years) | C17: 5 | D17: 5 | E17: 5 | F17: 4 | G17: 7
B18: Exit EBITDA ($M) | C18: 76.7 | D18: 91.8 | E18: 110.6 | F18: 84.2 | G18: 108.4
B19: Exit EV/EBITDA Multiple | C19: 14 | D19: 16 | E19: 18 | F19: 15 | G19: 15.5
B20: Exit Enterprise Value ($M) | C20: =C18*C19 -> 1073.8 | D20: =D18*D19 -> 1468.8 | E20: =E18*E19 -> 1990.8 | F20: =F18*F19 -> 1263 | G20: =G18*G19 -> 1680.2
B21: Exit Net Debt ($M) | C21: 292 | D21: 288 | E21: 284 | F21: 295 | G21: 278
B22: Exit Equity Value ($M) | C22: =C20-C21 -> 781.8 | D22: =D20-D21 -> 1180.8 | E22: =E20-E21 -> 1706.8 | F22: =F20-F21 -> 968 | G22: =G20-G21 -> 1402.2
C23: =C22 -> 781.8 | D23: =D22 -> 1180.8 | E23: =E22 -> 1706.8 | F23: =F22 -> 968 | G23: =G22 -> 1402.2
B24: RETURNS ANALYSIS
B25: Metric | C25: Bear (5yr) | D25: Base (5yr) | E25: Bull (5yr) | F25: Base (4yr) | G25: Base (7yr)
B26: Invested Equity ($M) | C26: 775 | D26: 775 | E26: 775 | F26: 775 | G26: 775
B27: Returned Equity ($M) | C27: 1395 | D27: 2015 | E27: 2712.5 | F27: 1860 | G27: 2247.5
B28: MOIC | C28: =C27/C26 -> 1.8 | D28: =D27/D26 -> 2.6 | E28: =E27/E26 -> 3.5 | F28: =F27/F26 -> 2.4 | G28: =G27/G26 -> 2.9
B29: IRR | C29: 0.14 | D29: 0.19 | E29: 0.25 | F29: 0.21 | G29: 0.17
B31: MOIC SENSITIVITY: EXIT MULTIPLE vs. EBITDA ($M)
B32: Exit Multiple ↓ | C32: $76.7M | D32: $84.0M | E32: $91.8M | F32: $100.0M | G32: $110.6M
B33: 12 | C33: 0.81 | D33: 0.93 | E33: 1.05 | F33: 1.17 | G33: 1.34
B34: 14 | C34: 1.01 | D34: 1.14 | E34: 1.28 | F34: 1.43 | G34: 1.62
B35: 16 | C35: 1.21 | D35: 1.36 | E35: 1.52 | F35: 1.69 | G35: 1.91
B36: 18 | C36: 1.41 | D36: 1.58 | E36: 1.76 | F36: 1.95 | G36: 2.19
B37: 20 | C37: 1.61 | D37: 1.79 | E37: 1.99 | F37: 2.21 | G37: 2.48
